netvis/__init__.py
netvis/admin.py
netvis/apps.py
netvis/models.py
netvis/tests.py
netvis/urls.py
netvis/utils.py
netvis/views.py
netvis/management/commands/__init__.py
netvis/management/commands/populate_netvis_cache.py
netvis/migrations/0001_initial.py
netvis/migrations/0002_alter_netviscache_id.py
netvis/migrations/__init__.py
netvis/static/netvis/css/netvis.css
netvis/static/netvis/js/netvis-simple.js
netvis/static/netvis/js/netvis.js
netvis/templates/netvis/gen_netvis.html
netvis/templates/netvis/load_js.html
netvis/templatetags/netvis_extras.py
acdh_django_netvis-3.1.0.dist-info/AUTHORS.rst
acdh_django_netvis-3.1.0.dist-info/LICENSE
acdh_django_netvis-3.1.0.dist-info/METADATA
acdh_django_netvis-3.1.0.dist-info/WHEEL
acdh_django_netvis-3.1.0.dist-info/top_level.txt
acdh_django_netvis-3.1.0.dist-info/RECORD
