Metadata-Version: 2.1
Name: acdh-django-netvis
Version: 3.1.0
Summary: App to visualize model objects as network graph
Home-page: https://github.com/acdh-oeaw/acdh-django-netvis
Author: Peter Andorfer
Author-email: peter.andorfer@oeaw.ac.at
License: MIT
Keywords: acdh_django_netvis
Platform: UNKNOWN
Classifier: Development Status :: 3 - Alpha
Classifier: Framework :: Django :: 2.0
Classifier: Intended Audience :: Developers
Classifier: License :: OSI Approved :: BSD License
Classifier: Natural Language :: English
Classifier: Programming Language :: Python :: 3.8
Requires-Dist: Django (>=3.1)
